plaid_lukepafford/__init__.py
plaid_lukepafford/main.py
plaid_lukepafford/transactions.py
plaid_lukepafford-0.1.7.dist-info/entry_points.txt
plaid_lukepafford-0.1.7.dist-info/WHEEL
plaid_lukepafford-0.1.7.dist-info/METADATA
plaid_lukepafford-0.1.7.dist-info/RECORD
