Metadata-Version: 2.1
Name: plaid-lukepafford
Version: 0.1.7
Summary: 
Author: Luke Pafford
Author-email: lukepafford@gmail.com
Requires-Python: >=3.7,<4.0
Classifier: Programming Language :: Python :: 3
Classifier: Programming Language :: Python :: 3.7
Classifier: Programming Language :: Python :: 3.8
Requires-Dist: pandas (>=1.0.5,<2.0.0)
Requires-Dist: plaid-python (>=4.1.0,<5.0.0)
Requires-Dist: pytest (>=5.4.3,<6.0.0)
Requires-Dist: typer (>=0.2.1,<0.3.0)
